surveil-0.16.1.dist-info/pbr.json
surveil-0.16.1.dist-info/metadata.json
surveil-0.16.1.dist-info/entry_points.txt
surveil-0.16.1.dist-info/top_level.txt
surveil-0.16.1.dist-info/WHEEL
surveil-0.16.1.dist-info/METADATA
surveil-0.16.1.dist-info/DESCRIPTION.rst
surveil-0.16.1.dist-info/RECORD
surveil/__init__.py
surveil/tests/base.py
surveil/tests/__init__.py
surveil/tests/integration/test_surveil.py
surveil/tests/integration/integration_test.py
surveil/tests/integration/__init__.py
surveil/tests/integration/backend/integration.yml
surveil/tests/integration/backend/docker_backend.py
surveil/tests/integration/backend/__init__.py
surveil/tests/cmd/__init__.py
surveil/tests/cmd/test_surveil_from_nagios.py
surveil/tests/cmd/nagios_config/other_file.cfg
surveil/tests/cmd/nagios_config/config.cfg
surveil/tests/api/functionalTest.py
surveil/tests/api/__init__.py
surveil/tests/api/policy.json
surveil/tests/api/controllers/__init__.py
surveil/tests/api/controllers/v2/test_hello.py
surveil/tests/api/controllers/v2/__init__.py
surveil/tests/api/controllers/v2/config/test_realms.py
surveil/tests/api/controllers/v2/config/test_businessimpactmodulations.py
surveil/tests/api/controllers/v2/config/test_services.py
surveil/tests/api/controllers/v2/config/test_checkmodulation.py
surveil/tests/api/controllers/v2/config/test_servicegroup.py
surveil/tests/api/controllers/v2/config/test_reload_config.py
surveil/tests/api/controllers/v2/config/test_commands.py
surveil/tests/api/controllers/v2/config/test_timeperiods.py
surveil/tests/api/controllers/v2/config/test_notificationways.py
surveil/tests/api/controllers/v2/config/test_hostgroup.py
surveil/tests/api/controllers/v2/config/test_contacts.py
surveil/tests/api/controllers/v2/config/test_contactgroup.py
surveil/tests/api/controllers/v2/config/__init__.py
surveil/tests/api/controllers/v2/config/test_macromodulations.py
surveil/tests/api/controllers/v2/config/test_hosts.py
surveil/tests/api/controllers/v2/auth/test_auth.py
surveil/tests/api/controllers/v2/auth/__init__.py
surveil/tests/api/controllers/v2/actions/test_downtime.py
surveil/tests/api/controllers/v2/actions/test_recheck.py
surveil/tests/api/controllers/v2/actions/test_acknowledge.py
