Metadata-Version: 2.0
Name: surveil
Version: 0.16.1
Summary: Monitoring as a Service for OpenStack
Home-page: UNKNOWN
Author: UNKNOWN
Author-email: UNKNOWN
License: UNKNOWN
Platform: UNKNOWN
Requires-Dist: pecan (>=0.5.0)
Requires-Dist: pymongo (>=2.7.2)
Requires-Dist: wsme
Requires-Dist: requests
Requires-Dist: watchdog
Requires-Dist: oslo.config
Requires-Dist: oslo.middleware
Requires-Dist: oslo.policy (>=0.3.0)
Requires-Dist: keystonemiddleware
Requires-Dist: PasteDeploy
Requires-Dist: influxdb (==2.8.0)
Requires-Dist: pika
Requires-Dist: python-surveilclient (==0.13.3)
Requires-Dist: six
Requires-Dist: docker-py
Requires-Dist: mongoengine
